ProxyScraper/_ProxyList.py
ProxyScraper/__init__.py
ProxyScraper/_adjisan_scraper.py
ProxyScraper/bin/ProxyList.py
ProxyScraper/bin/__init__.py
adjisan_proxy_scraper-0.1.1.dist-info/METADATA
adjisan_proxy_scraper-0.1.1.dist-info/WHEEL
adjisan_proxy_scraper-0.1.1.dist-info/top_level.txt
adjisan_proxy_scraper-0.1.1.dist-info/RECORD
