Metadata-Version: 2.1
Name: adjisan-proxy-scraper
Version: 0.1.1
Summary: Scrape fast HTTP, HTTPS, SOCKS4, and SOCKS5 proxies.
Home-page: https://github.com/adjidev/proxyscraper
Author: adjisan
Author-email: hello.adjisan@gmail.com
Classifier: Programming Language :: Python :: 3
Classifier: License :: OSI Approved :: MIT License
Classifier: Operating System :: OS Independent
Requires-Python: >=3.6
